AUTHORS.txt
CHANGELOG.txt
INSTALL.txt
LICENSE.txt
MANIFEST.in
README.txt
TODO.txt
setup.py
django_media_utils.egg-info/PKG-INFO
django_media_utils.egg-info/SOURCES.txt
django_media_utils.egg-info/dependency_links.txt
django_media_utils.egg-info/not-zip-safe
django_media_utils.egg-info/top_level.txt
media_utils/__init__.py
media_utils/models.py
media_utils/settings.py
media_utils/views.py
media_utils/management/__init__.py
media_utils/management/commands/__init__.py
media_utils/management/commands/link_media.py
media_utils/tests/__init__.py
media_utils/tests/runtests.py
media_utils/tests/test_cases.py
media_utils/tests/test_settings.py
media_utils/tests/test_urls.py
media_utils/tests/tests.py
media_utils/tests/no_label_app/__init__.py
media_utils/tests/no_label_app/media/file2.txt
media_utils/tests/skip_app/__init__.py
media_utils/tests/skip_app/media/skip_app/skip_file.txt
media_utils/tests/templates/404.html
media_utils/tests/test_app/__init__.py
media_utils/tests/test_app/media/test_app/file.txt
media_utils/tests/test_app/media/test_app/file1.txt
media_utils/tests/test_project/media/test.txt
media_utils/tests/test_project/media/subdir/test.txt
media_utils/tests/test_project/media/test_app/file.txt
media_utils/tests/test_project/media/test_app/file1.txt