Metadata-Version: 1.0
Name: django-media-utils
Version: 0.1.0
Summary: Django utilities for managing static assets
Home-page: http://launchpad.net/django-media-utils
Author: Carl Meyer
Author-email: carl@dirtcircle.com
License: UNKNOWN
Platform: UNKNOWN
Classifier: Development Status :: 3 - Alpha
Classifier: Environment :: Web Environment
Classifier: Intended Audience :: Developers
Classifier: License :: OSI Approved :: BSD License
Classifier: Operating System :: OS Independent
Classifier: Programming Language :: Python
Classifier: Framework :: Django
